azure/mgmt/mongodbatlas/__init__.py
azure/mgmt/mongodbatlas/_client.py
azure/mgmt/mongodbatlas/_configuration.py
azure/mgmt/mongodbatlas/_patch.py
azure/mgmt/mongodbatlas/_version.py
azure/mgmt/mongodbatlas/py.typed
azure/mgmt/mongodbatlas/_utils/__init__.py
azure/mgmt/mongodbatlas/_utils/model_base.py
azure/mgmt/mongodbatlas/_utils/serialization.py
azure/mgmt/mongodbatlas/aio/__init__.py
azure/mgmt/mongodbatlas/aio/_client.py
azure/mgmt/mongodbatlas/aio/_configuration.py
azure/mgmt/mongodbatlas/aio/_patch.py
azure/mgmt/mongodbatlas/aio/operations/__init__.py
azure/mgmt/mongodbatlas/aio/operations/_operations.py
azure/mgmt/mongodbatlas/aio/operations/_patch.py
azure/mgmt/mongodbatlas/models/__init__.py
azure/mgmt/mongodbatlas/models/_enums.py
azure/mgmt/mongodbatlas/models/_models.py
azure/mgmt/mongodbatlas/models/_patch.py
azure/mgmt/mongodbatlas/operations/__init__.py
azure/mgmt/mongodbatlas/operations/_operations.py
azure/mgmt/mongodbatlas/operations/_patch.py
azure_mgmt_mongodbatlas-1.0.0.dist-info/LICENSE
azure_mgmt_mongodbatlas-1.0.0.dist-info/METADATA
azure_mgmt_mongodbatlas-1.0.0.dist-info/WHEEL
azure_mgmt_mongodbatlas-1.0.0.dist-info/top_level.txt
azure_mgmt_mongodbatlas-1.0.0.dist-info/RECORD
